{"gameId":"8a89ef32-f99e-4f99-bb45-65180012f5c5","sessionId":"2s336z2g-cyu7st-mip2b9z0-1-mip2ba0l-4","type":"GAME_INIT","value":{"priorityTime":1500,"players":[{"name":"Computer 2","life":20,"counters":[],"battlefield":{}},{"name":"will","life":20,"counters":[],"battlefield":{}}],"stack":{},"combat":[]}}
{"gameId":"8a89ef32-f99e-4f99-bb45-65180012f5c5","sessionId":"2s336z2g-cyu7st-mip2b9z0-1-mip2ba0l-4","type":"GAME_UPDATE","value":{"priorityTime":1500,"players":[{"name":"Computer 2","life":20,"counters":[],"battlefield":{}},{"name":"will","life":20,"counters":[],"battlefield":{}}],"stack":{},"combat":[],"phase":"BEGINNING","step":"UPKEEP"}}
{"gameId":"8a89ef32-f99e-4f99-bb45-65180012f5c5","sessionId":"2s336z2g-cyu7st-mip2b9z0-1-mip2ba0l-4","type":"GAME_UPDATE","value":{"priorityTime":1500,"players":[{"name":"Computer 2","life":20,"counters":[],"battlefield":{}},{"name":"will","life":20,"counters":[],"battlefield":{}}],"stack":{},"combat":[],"phase":"BEGINNING","step":"UPKEEP"}}
{"gameId":"8a89ef32-f99e-4f99-bb45-65180012f5c5","sessionId":"2s336z2g-cyu7st-mip2b9z0-1-mip2ba0l-4","type":"GAME_OVER","value":{"gameView":{"priorityTime":1500,"players":[{"name":"Computer 2","life":20,"counters":[],"battlefield":{}},{"name":"will","life":20,"counters":[],"battlefield":{}}],"stack":{},"combat":[],"phase":"BEGINNING","step":"UPKEEP"},"message":"Game is a draw"}}
